google_auth_oauthlib/__init__.py
google_auth_oauthlib/flow.py
google_auth_oauthlib/helpers.py
google_auth_oauthlib/interactive.py
google_auth_oauthlib/tool/__init__.py
google_auth_oauthlib/tool/__main__.py
google_auth_oauthlib-1.0.0.dist-info/LICENSE
google_auth_oauthlib-1.0.0.dist-info/METADATA
google_auth_oauthlib-1.0.0.dist-info/WHEEL
google_auth_oauthlib-1.0.0.dist-info/entry_points.txt
google_auth_oauthlib-1.0.0.dist-info/top_level.txt
google_auth_oauthlib-1.0.0.dist-info/RECORD
