Metadata-Version: 2.1
Name: google-auth-oauthlib
Version: 1.0.0
Summary: Google Authentication Library
Home-page: https://github.com/GoogleCloudPlatform/google-auth-library-python-oauthlib
Author: Google Cloud Platform
Author-email: jonwayne+google-auth@google.com
License: Apache 2.0
Keywords: google auth oauth client oauthlib
Classifier: Programming Language :: Python :: 3
Classifier: Programming Language :: Python :: 3.6
Classifier: Programming Language :: Python :: 3.7
Classifier: Programming Language :: Python :: 3.8
Classifier: Programming Language :: Python :: 3.9
Classifier: Programming Language :: Python :: 3.10
Classifier: Programming Language :: Python :: 3.11
Classifier: Development Status :: 5 - Production/Stable
Classifier: Intended Audience :: Developers
Classifier: License :: OSI Approved :: Apache Software License
Classifier: Operating System :: POSIX
Classifier: Operating System :: Microsoft :: Windows
Classifier: Operating System :: MacOS :: MacOS X
Classifier: Operating System :: OS Independent
Classifier: Topic :: Internet :: WWW/HTTP
Requires-Python: >=3.6
Provides-Extra: tool
License-File: LICENSE
